envcon/__init__.py
envcon/configuration.py
envcon/configuration_injector.py
envcon/extended_environ.py
envcon/frozen.py
envcon/utils/__init__.py
envcon/utils/functional.py
envcon/utils/inspections.py
envcon/utils/type_utils.py
envcon-1.8.3.dist-info/LICENSE
envcon-1.8.3.dist-info/METADATA
envcon-1.8.3.dist-info/WHEEL
envcon-1.8.3.dist-info/RECORD
