Metadata-Version: 2.1
Name: envcon
Version: 1.8.3
Summary: envcon: environment variables parsing using type-hints
Home-page: https://github.com/neriat/envcon
License: MIT
Keywords: environment,variables,configuration,12factor,twelve-factor
Author: Neria
Author-email: me@neria.dev
Maintainer: Neria
Maintainer-email: me@neria.dev
Requires-Python: >=3.8.1,<4.0.0
Classifier: Intended Audience :: Developers
Classifier: License :: OSI Approved :: MIT License
Classifier: Natural Language :: English
Classifier: Operating System :: OS Independent
Classifier: Programming Language :: Python :: 3
Classifier: Programming Language :: Python :: 3.9
Classifier: Programming Language :: Python :: 3.10
Classifier: Programming Language :: Python :: 3.11
Classifier: Programming Language :: Python :: 3.12
Classifier: Programming Language :: Python :: 3.8
Classifier: Topic :: Software Development :: Libraries :: Python Modules
Classifier: Topic :: Utilities
Classifier: Typing :: Typed
Requires-Dist: python-dotenv (>=0.18.0,<2.0.0)
Project-URL: Repository, https://github.com/neriat/envcon
